{"cameraMode":{"drawMode":0,"name":"Shaded","section":"Shading Mode"},"sceneLighting":false,"audioPlay":false,"sceneViewState":{"m_AlwaysRefresh":false,"showFog":true,"showSkybox":false,"showFlares":true,"showImageEffects":true,"showParticleSystems":true,"showVisualEffectGraphs":true,"m_FxEnabled":true},"in2DMode":false,"pivot":{"x":0.01568603515625,"y":0.48889076709747317,"z":0.007983207702636719},"rotation":{"x":-0.07478681951761246,"y":-0.8416157364845276,"z":0.11275912821292877,"w":-0.523415744304657},"size":1.2296866178512574,"orthographic":false}